Metadata-Version: 1.0
Name: bae-distributions
Version: 0.1
Summary: Gaussian and Binomial distributions
Home-page: UNKNOWN
Author: Inbae Kang
Author-email: kibae92@gmail.com
License: UNKNOWN
Platform: UNKNOWN
